LICENSE
README.md
setup.py
flask_apm_watchlog.egg-info/PKG-INFO
flask_apm_watchlog.egg-info/SOURCES.txt
flask_apm_watchlog.egg-info/dependency_links.txt
flask_apm_watchlog.egg-info/requires.txt
flask_apm_watchlog.egg-info/top_level.txt
flask_watchlog_apm/__init__.py
flask_watchlog_apm/instrument.py